{
  "ocean": {
    "primary": {
      "50": "#ecfeff",
      "100": "#cffafe",
      "200": "#a5f3fc",
      "300": "#67e8f9",
      "400": "#22d3ee",
      "500": "#06b6d4",
      "600": "#0891b2",
      "700": "#0e7490",
      "800": "#155e75",
      "900": "#164e63"
    }
  },
  "rainforest": {
    "primary": {
      "50": "#ecfdf4",
      "100": "#c6f3dd",
      "200": "#9de9c6",
      "300": "#56d0a0",
      "400": "#00b380",
      "500": "#009268",
      "600": "#027451",
      "700": "#006344",
      "800": "#005038",
      "900": "#003422"
    }
  },
  "candy": {
    "primary": {
      "50": "#fdf2f8",
      "100": "#fce1f0",
      "200": "#fdc9e7",
      "300": "#fd9ed3",
      "400": "#f86ab6",
      "500": "#e82f91",
      "600": "#c00664",
      "700": "#a1004b",
      "800": "#84003d",
      "900": "#590028"
    }
  }
}
